odoo9_addon_document_page_environmental_aspect-9.0.1.0.0.99.dev8-py2.7-nspkg.pth
odoo9_addon_document_page_environmental_aspect-9.0.1.0.0.99.dev8.dist-info/DESCRIPTION.rst
odoo9_addon_document_page_environmental_aspect-9.0.1.0.0.99.dev8.dist-info/METADATA
odoo9_addon_document_page_environmental_aspect-9.0.1.0.0.99.dev8.dist-info/RECORD
odoo9_addon_document_page_environmental_aspect-9.0.1.0.0.99.dev8.dist-info/WHEEL
odoo9_addon_document_page_environmental_aspect-9.0.1.0.0.99.dev8.dist-info/metadata.json
odoo9_addon_document_page_environmental_aspect-9.0.1.0.0.99.dev8.dist-info/namespace_packages.txt
odoo9_addon_document_page_environmental_aspect-9.0.1.0.0.99.dev8.dist-info/top_level.txt
odoo_addons/document_page_environmental_aspect/README.rst
odoo_addons/document_page_environmental_aspect/__init__.py
odoo_addons/document_page_environmental_aspect/__openerp__.py
odoo_addons/document_page_environmental_aspect/data/document_page.xml
odoo_addons/document_page_environmental_aspect/i18n/de.po
odoo_addons/document_page_environmental_aspect/i18n/document_page_environmental_aspect.pot
odoo_addons/document_page_environmental_aspect/i18n/es.po
odoo_addons/document_page_environmental_aspect/i18n/es_CL.po
odoo_addons/document_page_environmental_aspect/i18n/fr.po
odoo_addons/document_page_environmental_aspect/i18n/id.po
odoo_addons/document_page_environmental_aspect/i18n/nb.po
odoo_addons/document_page_environmental_aspect/i18n/pt_BR.po
odoo_addons/document_page_environmental_aspect/i18n/sl.po
odoo_addons/document_page_environmental_aspect/i18n/sv.po
odoo_addons/document_page_environmental_aspect/i18n/vi.po
odoo_addons/document_page_environmental_aspect/migrations/7.0.1.0/pre-migration.py
odoo_addons/document_page_environmental_aspect/static/description/icon.png
odoo_addons/document_page_environmental_aspect/views/document_page.xml
